robottestlink/__init__.py
robottestlink/parsers.py
robottestlink/robottestlinkhelper.py
robottestlink/testlinklistener.py
robottestlink/utils.py
robottestlink-0.1.1.dist-info/DESCRIPTION.rst
robottestlink-0.1.1.dist-info/METADATA
robottestlink-0.1.1.dist-info/RECORD
robottestlink-0.1.1.dist-info/WHEEL
robottestlink-0.1.1.dist-info/metadata.json
robottestlink-0.1.1.dist-info/top_level.txt
